CL_Utility_Library/CL_Utility_Keywords.py
CL_Utility_Library/__init__.py
CL_Utility_Library-0.2.0.dist-info/LICENSE.txt
CL_Utility_Library-0.2.0.dist-info/METADATA
CL_Utility_Library-0.2.0.dist-info/WHEEL
CL_Utility_Library-0.2.0.dist-info/top_level.txt
CL_Utility_Library-0.2.0.dist-info/RECORD
